bas_geoplot/__init__.py
bas_geoplot/cli.py
bas_geoplot/interactive.py
bas_geoplot/utils.py
bas_geoplot/config/interactive.json
bas_geoplot-0.1.3.dist-info/LICENSE
bas_geoplot-0.1.3.dist-info/METADATA
bas_geoplot-0.1.3.dist-info/WHEEL
bas_geoplot-0.1.3.dist-info/entry_points.txt
bas_geoplot-0.1.3.dist-info/top_level.txt
bas_geoplot-0.1.3.dist-info/RECORD
