Metadata-Version: 2.2
Name: bas_geoplot
Version: 0.1.3
Summary: GeoPlot: BAS AI Lab plotting scripts for internal plotting & visualisation
Author-email: "Autonomous Marine Operations Planning (AMOP) Team, AI Lab, British Antarctic Survey" <amop@bas.ac.uk>
License: MIT License
Project-URL: Homepage, https://www.bas.ac.uk/project/autonomous-marine-operations-planning
Project-URL: Repository, https://github.com/bas-amop/GeoPlot
Project-URL: Issues, https://github.com/bas-amop/GeoPlot/issues
Keywords: Polar Science,Geoscience,Visualisation
Classifier: Intended Audience :: Science/Research
Classifier: Development Status :: 3 - Alpha
Classifier: License :: OSI Approved :: MIT License
Classifier: Natural Language :: English
Classifier: Operating System :: OS Independent
Classifier: Programming Language :: Python
Classifier: Programming Language :: Python :: 3
Classifier: Programming Language :: Python :: 3.8
Classifier: Programming Language :: Python :: 3.9
Classifier: Programming Language :: Python :: 3.10
Classifier: Programming Language :: Python :: 3.11
Classifier: Programming Language :: Python :: 3.12
Classifier: Programming Language :: Python :: 3.13
Classifier: Programming Language :: Python :: 3.14
Requires-Python: >=3.8
License-File: LICENSE
Requires-Dist: folium
Requires-Dist: geopandas
Requires-Dist: pandas>=1.3.5
Requires-Dist: branca
Requires-Dist: numpy
Requires-Dist: shapely
Requires-Dist: jinja2
Requires-Dist: urllib3<2
Requires-Dist: pyproj
